mls/__about__.py
mls/__init__.py
mls/cli.py
mls/manager/__init__.py
mls/manager/allocation/__init__.py
mls/manager/allocation/cli.py
mls/manager/allocation/help.py
mls/manager/configure/__init__.py
mls/manager/configure/cli.py
mls/manager/configure/custom_types.py
mls/manager/configure/help.py
mls/manager/configure/utils.py
mls/manager/dts/__init__.py
mls/manager/dts/connector_cli.py
mls/manager/dts/custom_types.py
mls/manager/dts/decorators.py
mls/manager/dts/help.py
mls/manager/dts/table.py
mls/manager/dts/transfer_cli.py
mls/manager/dts/utils.py
mls/manager/job/__init__.py
mls/manager/job/cli.py
mls/manager/job/constants.py
mls/manager/job/custom_types.py
mls/manager/job/dataclasses.py
mls/manager/job/decorators.py
mls/manager/job/help.py
mls/manager/job/utils.py
mls/manager/queue/__init__.py
mls/manager/queue/cli.py
mls/manager/queue/help.py
mls/schema/__init__.py
mls/schema/table.py
mls/utils/__init__.py
mls/utils/cli_entrypoint_help.py
mls/utils/client.py
mls/utils/common.py
mls/utils/common_types.py
mls/utils/execption.py
mls/utils/fomatter.py
mls/utils/openssl.py
mls/utils/settings.py
mls/utils/style.py
mls_core/__init__.py
mls_core/client.py
mls_core/exceptions.py
mls_core/setting.py
mls_core/allocation/__init__.py
mls_core/allocation/client.py
mls_core/queue/__init__.py
mls_core/queue/client.py
cloudru_ml_cli-0.11.1.dist-info/METADATA
cloudru_ml_cli-0.11.1.dist-info/WHEEL
cloudru_ml_cli-0.11.1.dist-info/entry_points.txt
cloudru_ml_cli-0.11.1.dist-info/licenses/LICENSE
cloudru_ml_cli-0.11.1.dist-info/RECORD
